authentik_cloud_gateway_client/__init__.py
authentik_cloud_gateway_client/authenticationPush_pb2.py
authentik_cloud_gateway_client/authenticationPush_pb2.pyi
authentik_cloud_gateway_client/authenticationPush_pb2_grpc.py
authentik_cloud_gateway_client/meta_pb2.py
authentik_cloud_gateway_client/meta_pb2.pyi
authentik_cloud_gateway_client/meta_pb2_grpc.py
authentik_cloud_gateway_client-0.4.0.dist-info/LICENSE
authentik_cloud_gateway_client-0.4.0.dist-info/METADATA
authentik_cloud_gateway_client-0.4.0.dist-info/WHEEL
authentik_cloud_gateway_client-0.4.0.dist-info/RECORD
