Metadata-Version: 2.1
Name: authentik_cloud_gateway_client
Version: 0.4.0
Summary: 
Author: authentik Team
Author-email: hello@goauthentik.io
Requires-Python: >=3.12,<3.13
Classifier: Programming Language :: Python :: 3
Classifier: Programming Language :: Python :: 3.12
Requires-Dist: grpcio
Requires-Dist: protobuf
